[
    {
        "id": 1,
        "nombre": "Ing Eneyder Garcia",
        "email": "admin@turnero.com",
        "password": "12345",
        "rol": "admin",
        "mesa": null
    },
    {
        "id": 2,
        "nombre": "Docente Ejemplo",
        "email": "docente@turnero.com",
        "password": "docente123",
        "rol": "docente",
        "mesa": 2
    },
    {
        "id": 6,
        "nombre": "soporte1",
        "email": "s1@abc.com",
        "password": "1234",
        "rol": "docente",
        "mesa": 1
    },
    {
        "id": 7,
        "nombre": "Sandra Campo",
        "email": "sandra@gmail.com",
        "password": "12345",
        "rol": "docente",
        "mesa": 3
    }
]